zintor.py
zintor-0.0.19.dist-info/METADATA
zintor-0.0.19.dist-info/WHEEL
zintor-0.0.19.dist-info/top_level.txt
zintor-0.0.19.dist-info/RECORD
