Metadata-Version: 2.1
Name: zintor
Version: 0.0.19
Summary: Python Admin Package
Home-page: UNKNOWN
Author: __Async__
License: UNKNOWN
Platform: UNKNOWN
Classifier: Programming Language :: Python :: 3
Classifier: License :: OSI Approved :: MIT License
Classifier: Operating System :: OS Independent
Requires-Python: >=3.8
Requires-Dist: Flask
Requires-Dist: Flask-Admin (>=1.6)
Requires-Dist: Flask-BabelEx
Requires-Dist: MarkupSafe (>=2)
Requires-Dist: WTForms (>=3)
Requires-Dist: flask-login
